xiaofeiwu/__init__.py
xiaofeiwu/lsgoxiaofeiwu.py
xiaofeiwu-0.0.1.dist-info/METADATA
xiaofeiwu-0.0.1.dist-info/WHEEL
xiaofeiwu-0.0.1.dist-info/top_level.txt
xiaofeiwu-0.0.1.dist-info/RECORD
